dependency_checker/__init__.py
dependency_checker/dpch.py
dependency_checker_dpch-1.0.4.dist-info/METADATA
dependency_checker_dpch-1.0.4.dist-info/WHEEL
dependency_checker_dpch-1.0.4.dist-info/entry_points.txt
dependency_checker_dpch-1.0.4.dist-info/top_level.txt
dependency_checker_dpch-1.0.4.dist-info/RECORD
