Metadata-Version: 2.1
Name: dependency-checker-dpch
Version: 1.0.4
Summary: Dependency checker for nodeJS
Home-page: https://github.com/dyte-submissions/dyte-vit-2022-jevin925
Author: Jevin Vekaria
Author-email: jevin925@gmail.com
License: MIT
Keywords: python package
Platform: UNKNOWN
Classifier: Programming Language :: Python :: 3
Classifier: License :: OSI Approved :: MIT License
Classifier: Operating System :: OS Independent
Requires-Dist: certifi (==2022.5.18.1)
Requires-Dist: charset-normalizer (==2.0.12)
Requires-Dist: et-xmlfile (==1.1.0)
Requires-Dist: idna (==3.3)
Requires-Dist: openpyxl (==3.0.10)
Requires-Dist: requests (==2.27.1)
Requires-Dist: urllib3 (==1.26.9)
